LICENSE
MANIFEST.in
README.md
setup.py
encryptedfiles/__init__.py
encryptedfiles/encryptedfile.py
encryptedfiles/encryptedjson.py
encryptedfiles/tests.py
encryptedfiles.egg-info/PKG-INFO
encryptedfiles.egg-info/SOURCES.txt
encryptedfiles.egg-info/dependency_links.txt
encryptedfiles.egg-info/requires.txt
encryptedfiles.egg-info/top_level.txt