Metadata-Version: 1.1
Name: encryptedfiles
Version: 0.0.4
Summary: Secure and easy to use encrypted files for Python.
Home-page: https://github.com/Skabed/encrypted-files
Author: skabed
Author-email: UNKNOWN
License: The MIT License (MIT)
